virelay/__init__.py
virelay/__main__.py
virelay/application.py
virelay/image_processing.py
virelay/model.py
virelay/py.typed
virelay/server.py
virelay/version.py
virelay/frontend/index.html
virelay/frontend/main-6KQZBFAP.js
virelay/frontend/polyfills-B6TNHZQ6.js
virelay/frontend/styles-D4IOHVWC.css
virelay/frontend/assets/favicon/apple-touch-icon.png
virelay/frontend/assets/favicon/favicon-48x48.png
virelay/frontend/assets/favicon/favicon.ico
virelay/frontend/assets/favicon/favicon.svg
virelay/frontend/assets/favicon/site.webmanifest
virelay/frontend/assets/favicon/web-app-manifest-192x192.png
virelay/frontend/assets/favicon/web-app-manifest-512x512.png
virelay/frontend/assets/images/circle-sprite.png
virelay/frontend/assets/images/virelay-logo.png
virelay-1.0.0.dist-info/METADATA
virelay-1.0.0.dist-info/WHEEL
virelay-1.0.0.dist-info/entry_points.txt
virelay-1.0.0.dist-info/licenses/COPYING
virelay-1.0.0.dist-info/RECORD
