Metadata-Version: 2.4
Name: virelay
Version: 1.0.0
Summary: ViRelAy is a web-based XAI tool for analyzing classifiers and their datasets by visualizing the source-data, attributions, clusterings, and embeddings as generated by tools like CoRelAy.
Project-URL: Documentation, https://virelay.readthedocs.io/en/latest/
Project-URL: Repository, https://github.com/virelay/virelay.git
Project-URL: Issues, https://github.com/virelay/virelay/issues
Project-URL: Changelog, https://github.com/virelay/virelay/blob/main/CHANGELOG.md
Author-email: "Christopher J. Anders" <contact@cjanders.de>, David Neumann <david.neumann@lecode.de>, Talmaj Marinc <talmaj@gmail.com>, Sebastian Lapuschkin <sebastian.lapuschkin@hhi.fraunhofer.de>, Pattarawat Chormai <pat.chormai@gmail.com>
Maintainer-email: David Neumann <david.neumann@lecode.de>, "Christopher J. Anders" <contact@cjanders.de>
License-Expression: AGPL-3.0-or-later
License-File: COPYING
Keywords: Artificial Intelligence,Deep Learning,Explainable AI,Interpretability,Machine Learning,SpRAy,Spectral Relevance Analysis,ViRelAy,Visual Analytics,XAI
Classifier: Development Status :: 4 - Beta
Classifier: Intended Audience :: Science/Research
Classifier: License :: OSI Approved :: GNU Affero General Public License v3 or later (AGPLv3+)
Classifier: Natural Language :: English
Classifier: Programming Language :: Python :: 3.11
Classifier: Programming Language :: Python :: 3.12
Classifier: Programming Language :: Python :: 3.13
Classifier: Topic :: Scientific/Engineering :: Artificial Intelligence
Classifier: Typing :: Typed
Requires-Python: >=3.11.13
Requires-Dist: flask-cors<7.0.0,>=6.0.1
Requires-Dist: flask<4.0.0,>=3.1.1
Requires-Dist: gunicorn<24.0.0,>=23.0.0
Requires-Dist: h5py<4.0.0,>=3.14.0
Requires-Dist: matplotlib<4.0.0,>=3.10.5
Requires-Dist: numpy<2.3.0,>=2.2.6
Requires-Dist: pillow<12.0.0,>=11.3.0
Requires-Dist: pyyaml<7.0.0,>=6.0.2
Requires-Dist: typing-extensions<5.0.0,>=4.14.1
Provides-Extra: examples
Requires-Dist: corelay[hdbscan,umap]<2.0.0,>=1.0.0; extra == 'examples'
Requires-Dist: numba<1.0.0,>=0.61.2; extra == 'examples'
Requires-Dist: scikit-image<1.0.0,>=0.25.2; extra == 'examples'
Requires-Dist: scipy<2.0.0,>=1.16.1; extra == 'examples'
Requires-Dist: zennit<2.0.0,>=1.0.0; extra == 'examples'
